coremail/__init__.py
coremail/client.py
coremail/models.py
coremail/typings/__init__.py
coremail-0.2.0.dist-info/licenses/LICENSE
coremail-0.2.0.dist-info/METADATA
coremail-0.2.0.dist-info/WHEEL
coremail-0.2.0.dist-info/top_level.txt
coremail-0.2.0.dist-info/RECORD
