Metadata-Version: 2.4
Name: coremail
Version: 0.2.0
Summary: A comprehensive Python SDK for interacting with Coremail XT API
Author-email: liudonghua <liudonghua123@gmail.com>
Maintainer-email: liudonghua <liudonghua123@gmail.com>
License: MIT
Project-URL: Homepage, https://github.com/liudonghua123/coremail
Project-URL: Documentation, https://github.com/liudonghua123/coremail#readme
Project-URL: Repository, https://github.com/liudonghua123/coremail
Project-URL: Changelog, https://github.com/liudonghua123/coremail/releases
Project-URL: Issues, https://github.com/liudonghua123/coremail/issues
Keywords: coremail,email,sdk,api,email-management,email-server
Classifier: Development Status :: 4 - Beta
Classifier: Intended Audience :: Developers
Classifier: License :: OSI Approved :: MIT License
Classifier: Operating System :: OS Independent
Classifier: Programming Language :: Python :: 3
Classifier: Programming Language :: Python :: 3.8
Classifier: Programming Language :: Python :: 3.9
Classifier: Programming Language :: Python :: 3.10
Classifier: Programming Language :: Python :: 3.11
Classifier: Programming Language :: Python :: 3.12
Classifier: Programming Language :: Python :: 3.13
Classifier: Programming Language :: Python :: 3.14
Classifier: Topic :: Software Development :: Libraries :: Python Modules
Classifier: Topic :: Communications :: Email
Requires-Python: >=3.8
License-File: LICENSE
Requires-Dist: requests>=2.25.0
Requires-Dist: python-dotenv>=0.19.0
Requires-Dist: cachetools>=5.0.0
Requires-Dist: pydantic>=2.0.0
Provides-Extra: dev
Requires-Dist: pytest>=7.0.0; extra == "dev"
Requires-Dist: pytest-mock>=3.8.0; extra == "dev"
Requires-Dist: pytest-cov>=4.0.0; extra == "dev"
Requires-Dist: responses>=0.23.0; extra == "dev"
Requires-Dist: mypy>=0.950; extra == "dev"
Requires-Dist: black>=22.0.0; extra == "dev"
Requires-Dist: flake8>=4.0.0; extra == "dev"
Requires-Dist: types-requests>=2.25.0; extra == "dev"
Requires-Dist: types-cachetools>=5.0.0; extra == "dev"
Requires-Dist: build>=0.10.0; extra == "dev"
Requires-Dist: twine>=4.0.0; extra == "dev"
Dynamic: license-file
